clevercloud_cdktf_provider_clevercloud/__init__.py
clevercloud_cdktf_provider_clevercloud/py.typed
clevercloud_cdktf_provider_clevercloud/_jsii/__init__.py
clevercloud_cdktf_provider_clevercloud/_jsii/cdktf-bindings@1.0.0.jsii.tgz
clevercloud_cdktf_provider_clevercloud/addon/__init__.py
clevercloud_cdktf_provider_clevercloud/cellar/__init__.py
clevercloud_cdktf_provider_clevercloud/cellar_bucket/__init__.py
clevercloud_cdktf_provider_clevercloud/configprovider/__init__.py
clevercloud_cdktf_provider_clevercloud/data_clevercloud_default_loadbalancer/__init__.py
clevercloud_cdktf_provider_clevercloud/docker/__init__.py
clevercloud_cdktf_provider_clevercloud/dotnet/__init__.py
clevercloud_cdktf_provider_clevercloud/drain_datadog/__init__.py
clevercloud_cdktf_provider_clevercloud/drain_elasticsearch/__init__.py
clevercloud_cdktf_provider_clevercloud/drain_http/__init__.py
clevercloud_cdktf_provider_clevercloud/drain_newrelic/__init__.py
clevercloud_cdktf_provider_clevercloud/drain_ovh/__init__.py
clevercloud_cdktf_provider_clevercloud/drain_syslog_tcp/__init__.py
clevercloud_cdktf_provider_clevercloud/drain_syslog_udp/__init__.py
clevercloud_cdktf_provider_clevercloud/elasticsearch/__init__.py
clevercloud_cdktf_provider_clevercloud/frankenphp/__init__.py
clevercloud_cdktf_provider_clevercloud/fsbucket/__init__.py
clevercloud_cdktf_provider_clevercloud/go/__init__.py
clevercloud_cdktf_provider_clevercloud/java_war/__init__.py
clevercloud_cdktf_provider_clevercloud/keycloak/__init__.py
clevercloud_cdktf_provider_clevercloud/materia_kv/__init__.py
clevercloud_cdktf_provider_clevercloud/matomo/__init__.py
clevercloud_cdktf_provider_clevercloud/metabase/__init__.py
clevercloud_cdktf_provider_clevercloud/mongodb/__init__.py
clevercloud_cdktf_provider_clevercloud/mysql/__init__.py
clevercloud_cdktf_provider_clevercloud/networkgroup/__init__.py
clevercloud_cdktf_provider_clevercloud/nodejs/__init__.py
clevercloud_cdktf_provider_clevercloud/otoroshi/__init__.py
cdktf_provider_clevercloud-1.0.0.dist-info/LICENSE
cdktf_provider_clevercloud-1.0.0.dist-info/METADATA
cdktf_provider_clevercloud-1.0.0.dist-info/WHEEL
cdktf_provider_clevercloud-1.0.0.dist-info/top_level.txt
cdktf_provider_clevercloud-1.0.0.dist-info/RECORD
